stlinmc/__main__.py
stlinmc/minecraft.py
stlinmc/voxel.py
stl_in_mc-0.2.0.dist-info/METADATA
stl_in_mc-0.2.0.dist-info/WHEEL
stl_in_mc-0.2.0.dist-info/entry_points.txt
stl_in_mc-0.2.0.dist-info/RECORD
