Metadata-Version: 2.1
Name: stl-in-mc
Version: 0.2.0
Summary: Import STL files into Minecraft
Home-page: https://github.com/martinmiglio/stl-in-mc
License: MIT
Keywords: memu,memuc,wrapper,api
Author: Martin Miglio
Author-email: code@martinmiglio.dev
Requires-Python: >=3.9,<3.13
Classifier: License :: OSI Approved :: MIT License
Classifier: Programming Language :: Python
Classifier: Programming Language :: Python :: 3
Classifier: Programming Language :: Python :: 3.9
Classifier: Programming Language :: Python :: 3.10
Classifier: Programming Language :: Python :: 3.11
Classifier: Topic :: Software Development :: Libraries :: Python Modules
Requires-Dist: mcpi (>=1.2.1,<2.0.0)
Requires-Dist: numpy (>=1.26.0,<2.0.0)
Requires-Dist: numpy-stl (>=2.17,<3.0)
Requires-Dist: stl-to-voxel (>=0.9.3,<0.10.0)
Requires-Dist: validators (>=0.22.0,<0.23.0)
Project-URL: Repository, https://github.com/martinmiglio/stl-in-mc
